LICENSE.txt
MANIFEST.in
README.md
UrlTasker.py
pyproject.toml
setup.cfg
setup.py
UrlTasker.egg-info/PKG-INFO
UrlTasker.egg-info/SOURCES.txt
UrlTasker.egg-info/dependency_links.txt
UrlTasker.egg-info/entry_points.txt
UrlTasker.egg-info/top_level.txt