Metadata-Version: 2.2
Name: UrlTasker
Version: 0.0.1
Summary: A Python library for defining, templating, and executing configurable asynchronous actions triggered via URLs.
Home-page: https://github.com/mauricelambert/UrlTasker
Author: Maurice Lambert
Author-email: Maurice Lambert <mauricelambert434@gmail.com>
Maintainer: Maurice Lambert
Maintainer-email: Maurice Lambert <mauricelambert434@gmail.com>
License: GPL-3.0 License
Project-URL: Github, https://github.com/mauricelambert/UrlTasker
Project-URL: Documentation, https://mauricelambert.github.io/info/python/code/UrlTasker.html
Keywords: url,task,async,async-tasker,asynchronous
Platform: Windows
Platform: Linux
Platform: MacOS
Classifier: Operating System :: POSIX
Classifier: Natural Language :: English
Classifier: Topic :: System :: Networking
Classifier: Topic :: Internet :: WWW/HTTP
Classifier: Programming Language :: Python
Classifier: Intended Audience :: Developers
Classifier: Operating System :: MacOS :: MacOS X
Classifier: Programming Language :: Python :: 3.8
Classifier: Operating System :: Microsoft :: Windows
Classifier: Topic :: System :: Systems Administration
Classifier: Intended Audience :: System Administrators
Classifier: Topic :: Software Development :: Libraries
Classifier: Development Status :: 5 - Production/Stable
Classifier: License :: OSI Approved :: GNU General Public License v3 or later (GPLv3+)
Requires-Python: >=3.8
License-File: LICENSE.txt
Dynamic: author
Dynamic: home-page
Dynamic: maintainer
Dynamic: requires-python
